{
  "A124": "A124.jpg",
  "A339": "A339.jpg",
  "A20N": "A20N.jpg",
  "B212": "B212.jpg",
  "A333": "A333.jpg",
  "B734": "B734.jpg",
  "A310": "A310.jpg",
  "B736": "B736.jpg",
  "AT72": "AT72.jpg",
  "BL8": "BL8.jpg",
  "AT45": "AT45.jpg",
  "B463": "B463.jpg",
  "A210": "A210.jpg",
  "AN32": "AN32.jpg",
  "A337": "A337.jpg",
  "RJ70": "RJ70.jpg",
  "BCS3": "BCS3.jpg",
  "A318": "A318.jpg",
  "A158": "A158.jpg",
  "AT76": "AT76.jpg",
  "A321": "A321.jpg",
  "AT73": "AT73.jpg",
  "A346": "A346.jpg",
  "A3ST": "A3ST.jpg",
  "A320": "A320.jpg",
  "A319": "A319.jpg",
  "BER2": "BER2.jpg",
  "B721": "B721.jpg",
  "A338": "A338.jpg",
  "A343": "A343.jpg",
  "A388": "A388.jpg",
  "A148": "A148.jpg",
  "AN26": "AN26.jpg",
  "B743": "B743.jpg",
  "AN72": "AN72.jpg",
  "B720": "B720.jpg",
  "B429": "B429.jpg",
  "RJ85": "RJ85.jpg",
  "B462": "B462.jpg",
  "A342": "A342.jpg",
  "B412": "B412.jpg",
  "CH7A": "CH7A.jpg",
  "B742": "B742.jpg",
  "B461": "B461.jpg",
  "A345": "A345.jpg",
  "AP22": "AP22.jpg",
  "B722": "B722.jpg",
  "BE58": "BE58.jpg",
  "A359": "A359.jpg",
  "S601": "S601.jpg",
  "BLCF": "BLCF.jpg",
  "A30B": "A30B.jpg",
  "B744": "B744.jpg",
  "AN30": "AN30.jpg",
  "B39M": "B39M.jpg",
  "B741": "B741.jpg",
  "B733": "B733.jpg",
  "B38M": "B38M.jpg",
  "B712": "B712.jpg",
  "A19N": "A19N.jpg",
  "B737": "B737.jpg",
  "BE55": "BE55.jpg",
  "B732": "B732.jpg",
  "BCS1": "BCS1.jpg",
  "A140": "A140.jpg",
  "AN12": "AN12.jpg",
  "AN28": "AN28.jpg",
  "AT75": "AT75.jpg",
  "B37M": "B37M.jpg",
  "N262": "N262.JPG",
  "AT43": "AT43.jpg",
  "A21N": "A21N.jpg",
  "A332": "A332.jpg",
  "B703": "B703.jpg",
  "B739": "B739.jpg",
  "B738": "B738.jpg",
  "B190": "B190.jpg",
  "RJ1H": "RJ1H.jpg",
  "B3XM": "B3XM.jpg",
  "CH7B": "CH7B.jpg",
  "A306": "A306.jpg",
  "A225": "A225.jpg",
  "B735": "B735.jpg",
  "AT46": "AT46.jpg",
  "AN24": "AN24.jpg",
  "B748": "B748.jpg",
  "B74R": "B74R.jpg",
  "B763": "B763.jpg",
  "B77L": "B77L.jpg",
  "B752": "B752.jpg",
  "B773": "B773.jpg",
  "H25B": "H25B.jpg",
  "CL2T": "CL2T.jpg",
  "GLEX": "GLEX.jpg",
  "B778": "B778.jpg",
  "B753": "B753.jpg",
  "B788": "B788.jpg",
  "B74S": "B74S.jpg",
  "B772": "B772.jpg",
  "B762": "B762.jpg",
  "CRJ7": "CRJ7.jpg",
  "JS41": "JS41.jpg",
  "B764": "B764.jpg",
  "CL30": "CL30.jpg",
  "B779": "B779.jpg",
  "H25C": "H25C.jpg",
  "C162": "C162.jpg",
  "B78X": "B78X.jpg",
  "GL5T": "GL5T.jpg",
  "CRJX": "CRJX.jpg",
  "C25B": "C25B.jpg",
  "JS31": "JS31.jpg",
  "ATP": "ATP.jpg",
  "CRJ9": "CRJ9.jpg",
  "C206": "C206.jpg",
  "CL60": "CL60.jpg",
  "CN35": "CN35.jpg",
  "DHC5": "DHC5.jpg",
  "B77W": "B77W.jpg",
  "F900": "F900.jpg",
  "C650": "C650.jpg",
  "C77R": "C77R.jpg",
  "C25A": "C25A.jpg",
  "C510": "C510.jpg",
  "CRJ1": "CRJ1.jpg",
  "HERN": "HERN.jpg",
  "JS32": "JS32.jpg",
  "SF50": "SF50.jpg",
  "C172": "C172.JPG",
  "C25C": "C25C.jpg",
  "B789": "B789.jpg",
  "C525": "C525.jpg",
  "C310": "C310.jpg",
  "DHC6": "DHC6.jpg",
  "BA11": "BA11.jpg",
  "C208": "C208.jpg",
  "DH8C": "DH8C.jpg",
  "DHC2": "DHC2.jpg",
  "C46": "C46.jpg",
  "C500": "C500.jpg",
  "CRJ2": "CRJ2.jpg",
  "DC10": "DC10.jpg",
  "CVLT": "CVLT.jpg",
  "C152": "C152.jpg",
  "C182": "C182.jpg",
  "C212": "C212.jpg",
  "DH8D": "DH8D.jpg",
  "DC85": "DC85.jpg",
  "C550": "C550.jpg",
  "C72R": "C72R.jpg",
  "C750": "C750.jpg",
  "DA42": "DA42.jpg",
  "CVLP": "CVLP.jpg",
  "DH8B": "DH8B.jpg",
  "C210": "C210.jpg",
  "DHC4": "DHC4.jpg",
  "FA7X": "FA7X.jpg",
  "C560": "C560.jpg",
  "DOVE": "DOVE.jpg",
  "DC6": "DC6.jpg",
  "C56X": "C56X.jpg",
  "C680": "C680.jpg",
  "FA50": "FA50.jpg",
  "C919": "C919.jpg",
  "DHC3": "DHC3.jpg",
  "DH8A": "DH8A.jpg",
  "DH2T": "DH2T.jpg",
  "F2TH": "F2TH.jpg",
  "DHC7": "DHC7.jpg",
  "DC3": "DC3.jpg",
  "DA62": "DA62.jpg",
  "DC91": "DC91.jpg",
  "DC87": "DC87.jpg",
  "DC95": "DC95.jpg",
  "DC93": "DC93.jpg",
  "E75L": "E75L.jpg",
  "E35L": "E35L.jpg",
  "E120": "E120.jpg",
  "E190": "E190.jpg",
  "E290": "E290.jpg",
  "E295": "E295.jpg",
  "DC92": "DC92.jpg",
  "E550": "E550.jpg",
  "EC35": "EC35.jpg",
  "E135": "E135.jpg",
  "GA8": "GA8.jpg",
  "DC94": "DC94.jpg",
  "J328": "J328.jpg",
  "AS50": "AS50.jpg",
  "AS32": "AS32.jpg",
  "S65C": "S65C.jpg",
  "F28": "F28.jpg",
  "E50P": "E50P.jpg",
  "F100": "F100.jpg",
  "G280": "G280.jpg",
  "DC86": "DC86.jpg",
  "G159": "G159.jpg",
  "D328": "D328.jpg",
  "E170": "E170.jpg",
  "F70": "F70.jpg",
  "EV97": "EV97.jpg",
  "EC25": "EC25.jpg",
  "G21": "G21.jpg",
  "E195": "E195.jpg",
  "E55P": "E55P.jpg",
  "GLF4": "GLF4.jpg",
  "A748": "A748.jpg",
  "AC90": "AC90.jpg",
  "E545": "E545.jpg",
  "AC68": "AC68.jpg",
  "E75S": "E75S.jpg",
  "IL62": "IL62.jpg",
  "I114": "I114.jpg",
  "JU52": "JU52.jpg",
  "F27": "F27.jpg",
  "EC45": "EC45.jpg",
  "F50": "F50.jpg",
  "L410": "L410.jpg",
  "A5": "A5.jpg",
  "EVSS": "EVSS.jpg",
  "CONI": "CONI.jpg",
  "MD83": "MD83.jpg",
  "D228": "D228.jpg",
  "IL96": "IL96.jpg",
  "MD11": "MD11.jpg",
  "E110": "E110.jpg",
  "B105": "B105.jpg",
  "E145": "E145.jpg",
  "EC20": "EC20.jpg",
  "G73T": "G73T.jpg",
  "GLF5": "GLF5.jpg",
  "Y12": "Y12.jpg",
  "MI24": "MI24.jpg",
  "IL86": "IL86.jpg",
  "GLF6": "GLF6.jpg",
  "NOMA": "NOMA.jpg",
  "IL76": "IL76.jpg",
  "HDJT": "HDJT.jpg",
  "MU2": "MU2.jpg",
  "P28B": "P28B.jpg",
  "WW24": "WW24.jpg",
  "C130": "C130.jpg",
  "P180": "P180.jpg",
  "IL18": "IL18.jpg",
  "LJ35": "LJ35.jpg",
  "MD88": "MD88.jpg",
  "LJ60": "LJ60.jpg",
  "PISI": "PISI.jpg",
  "L101": "L101.jpg",
  "BN2P": "BN2P.jpg",
  "PA31": "PA31.jpg",
  "MD87": "MD87.jpg",
  "L188": "L188.jpg",
  "YS11": "YS11.jpg",
  "MI8": "MI8.jpg",
  "MD81": "MD81.jpg",
  "TRIS": "TRIS.jpg",
  "MD90": "MD90.jpg",
  "PA44": "PA44.jpg",
  "MD82": "MD82.jpg",
  "PC12": "PC12.jpg",
  "P68": "P68.jpg",
  "EXPL": "EXPL.jpg",
  "P28A": "P28A.jpg",
  "PC6T": "PC6T.jpg",
  "PA46": "PA46.jpg",
  "BELF": "BELF.jpg",
  "PIVI": "PIVI.jpg",
  "ATL": "ATL.jpg",
  "SF34": "SF34.jpg",
  "F406": "F406.jpg",
  "SC7": "SC7.jpg",
  "PITA": "PITA.jpg",
  "SIRA": "SIRA.jpg",
  "S58T": "S58T.jpg",
  "T154": "T154.jpg",
  "R200": "R200.jpg",
  "TRF1": "TRF1.jpg",
  "S76": "S76.jpg",
  "ECHO": "ECHO.jpg",
  "S61": "S61.jpg",
  "TWEN": "TWEN.jpg",
  "YK42": "YK42.jpg",
  "SU95": "SU95.jpg",
  "T134": "T134.jpg",
  "P212": "P212.jpg",
  "SB20": "SB20.jpg",
  "SH33": "SH33.jpg",
  "SH36": "SH36.jpg",
  "S92": "S92.jpg",
  "TB20": "TB20.jpg",
  "P06T": "P06T.jpg",
  "P208": "P208.jpg",
  "GOLF": "GOLF.jpg",
  "T204": "T204.jpg",
  "TL20": "TL20.jpg",
  "YK40": "YK40.jpg",
  "A35K": "A35K.jpg",
  "GA7C": "GA7C.jpg"
}
